hpcai/__init__.py
hpcai/_base_client.py
hpcai/_client.py
hpcai/_compat.py
hpcai/_constants.py
hpcai/_exceptions.py
hpcai/_files.py
hpcai/_models.py
hpcai/_qs.py
hpcai/_resource.py
hpcai/_response.py
hpcai/_streaming.py
hpcai/_types.py
hpcai/_version.py
hpcai/checkpoint_utils.py
hpcai/py.typed
hpcai/_utils/__init__.py
hpcai/_utils/_logs.py
hpcai/_utils/_proxy.py
hpcai/_utils/_reflection.py
hpcai/_utils/_resources_proxy.py
hpcai/_utils/_streams.py
hpcai/_utils/_sync.py
hpcai/_utils/_transform.py
hpcai/_utils/_typing.py
hpcai/_utils/_utils.py
hpcai/cookbook/README.md
hpcai/cookbook/__init__.py
hpcai/cookbook/checkpoint_utils.py
hpcai/cookbook/cli_utils.py
hpcai/cookbook/common.py
hpcai/cookbook/completers.py
hpcai/cookbook/context_manager.py
hpcai/cookbook/data.py
hpcai/cookbook/display.py
hpcai/cookbook/model_info.py
hpcai/cookbook/renderers.py
hpcai/cookbook/tokenizer_utils.py
hpcai/cookbook/eval/__init__.py
hpcai/cookbook/eval/custom_evaluators.py
hpcai/cookbook/eval/custom_inspect_task.py
hpcai/cookbook/eval/evaluators.py
hpcai/cookbook/eval/inspect_evaluators.py
hpcai/cookbook/eval/inspect_utils.py
hpcai/cookbook/eval/run_inspect_evals.py
hpcai/cookbook/recipes/rl_basic.py
hpcai/cookbook/recipes/rl_loop.py
hpcai/cookbook/recipes/sl_basic.py
hpcai/cookbook/recipes/sl_loop.py
hpcai/cookbook/recipes/chat_sl/__init__.py
hpcai/cookbook/recipes/chat_sl/chat_datasets.py
hpcai/cookbook/recipes/chat_sl/train.py
hpcai/cookbook/recipes/math_rl/__init__.py
hpcai/cookbook/recipes/math_rl/arithmetic_env.py
hpcai/cookbook/recipes/math_rl/math_env.py
hpcai/cookbook/recipes/math_rl/math_grading.py
hpcai/cookbook/recipes/math_rl/train.py
hpcai/cookbook/rl/__init__.py
hpcai/cookbook/rl/data_processing.py
hpcai/cookbook/rl/metric_util.py
hpcai/cookbook/rl/metrics.py
hpcai/cookbook/rl/play_w_env.py
hpcai/cookbook/rl/preference_envs.py
hpcai/cookbook/rl/problem_env.py
hpcai/cookbook/rl/rollouts.py
hpcai/cookbook/rl/train.py
hpcai/cookbook/rl/types.py
hpcai-0.2.0.dist-info/METADATA
hpcai-0.2.0.dist-info/WHEEL
hpcai-0.2.0.dist-info/licenses/LICENSE
hpcai-0.2.0.dist-info/licenses/NOTICE
hpcai-0.2.0.dist-info/RECORD
