Metadata-Version: 2.3
Name: hpcai
Version: 0.2.0
Summary: Python SDK for HPC-AI cloud GPU fine-tuning
Project-URL: Homepage, https://hpc-ai.com
Project-URL: Repository, https://github.com/hpcaitech/HPC-AI-SDK
Project-URL: Documentation, https://www.hpc-ai.com/doc
Author-email: "HPC AI TECHNOLOGY PTE. LTD." <service@hpc-ai.com>
License: Apache-2.0
Keywords: distributed training,fine-tuning,gpu,hpcai,machine learning
Classifier: Intended Audience :: Developers
Classifier: License :: OSI Approved :: Apache Software License
Classifier: Operating System :: MacOS
Classifier: Operating System :: Microsoft :: Windows
Classifier: Operating System :: OS Independent
Classifier: Operating System :: POSIX
Classifier: Operating System :: POSIX :: Linux
Classifier: Programming Language :: Python :: 3.9
Classifier: Programming Language :: Python :: 3.10
Classifier: Programming Language :: Python :: 3.11
Classifier: Programming Language :: Python :: 3.12
Classifier: Programming Language :: Python :: 3.13
Classifier: Topic :: Software Development :: Libraries :: Python Modules
Classifier: Typing :: Typed
Requires-Python: >=3.9
Requires-Dist: aiohttp
Requires-Dist: anyio<5,>=3.5.0
Requires-Dist: blobfile
Requires-Dist: chz
Requires-Dist: datasets
Requires-Dist: distro<2,>=1.7.0
Requires-Dist: httpx-aiohttp>=0.1.8
Requires-Dist: httpx[http2]<1,>=0.23.0
Requires-Dist: logtree
Requires-Dist: neptune-scale
Requires-Dist: nest-asyncio
Requires-Dist: numpy<2.0.0,>=1.24.0
Requires-Dist: pydantic<3,>=1.9.0
Requires-Dist: pylatexenc
Requires-Dist: sniffio
Requires-Dist: termcolor
Requires-Dist: torch>=2.0.0
Requires-Dist: trackio
Requires-Dist: transformers>=4.30.0
Requires-Dist: typing-extensions<5,>=4.10
Requires-Dist: wandb
